Metadata-Version: 2.1
Name: whispers
Version: 2.4.0
Summary: Identify secrets in static structured text
Home-page: https://github.com/adeptex/whispers
Author: Artëm Tsvetkov
Author-email: adeptex@users.noreply.github.com
Platform: any
Classifier: License :: OSI Approved :: BSD License
License-File: LICENSE
Requires-Dist: beautifulsoup4==4.12.3
Requires-Dist: crossplane==0.5.8
Requires-Dist: jellyfish==1.1.0
Requires-Dist: jproperties==2.1.1
Requires-Dist: jsonschema==4.23.0
Requires-Dist: jsonschema-specifications==2023.12.1
Requires-Dist: luhn==0.2.0
Requires-Dist: lxml==5.3.0
Requires-Dist: PyYAML==6.0.2
Requires-Dist: six==1.16.0
Requires-Dist: soupsieve==2.6
Requires-Dist: typing-extensions==4.12.2
Requires-Dist: wrapt==1.16.0
Requires-Dist: semgrep==1.85.0; sys_platform != "win32"
Provides-Extra: dev
Requires-Dist: autoflake~=2.3; extra == "dev"
Requires-Dist: autopep8~=2.3; extra == "dev"
Requires-Dist: black~=24.8; extra == "dev"
Requires-Dist: build~=1.2; extra == "dev"
Requires-Dist: coverage~=7.6; extra == "dev"
Requires-Dist: coverage-badge~=1.1; extra == "dev"
Requires-Dist: flake8~=7.1; extra == "dev"
Requires-Dist: isort~=5.13; extra == "dev"
Requires-Dist: pytest~=8.3; extra == "dev"
Requires-Dist: pytest-mock~=3.14; extra == "dev"
Requires-Dist: pip-tools~=7.4; extra == "dev"
Requires-Dist: wheel~=0.44; extra == "dev"
Requires-Dist: twine~=5.1; extra == "dev"
